{
  "id": "759046",
  "name": "web3.0",
  "font_family": "iconfont",
  "css_prefix_text": "icon-",
  "description": "",
  "glyphs": [
    {
      "icon_id": "14178954",
      "name": "eam",
      "font_class": "eam",
      "unicode": "e73c",
      "unicode_decimal": 59196
    },
    {
      "icon_id": "13871025",
      "name": "fulu",
      "font_class": "fulu",
      "unicode": "e739",
      "unicode_decimal": 59193
    },
    {
      "icon_id": "13871014",
      "name": "beizhu",
      "font_class": "beizhu",
      "unicode": "e73a",
      "unicode_decimal": 59194
    },
    {
      "icon_id": "13871015",
      "name": "yizhuan",
      "font_class": "yizhuan",
      "unicode": "e73b",
      "unicode_decimal": 59195
    },
    {
      "icon_id": "13497474",
      "name": "goout",
      "font_class": "goout",
      "unicode": "e738",
      "unicode_decimal": 59192
    },
    {
      "icon_id": "13416559",
      "name": "dianbao",
      "font_class": "dianbao",
      "unicode": "e736",
      "unicode_decimal": 59190
    },
    {
      "icon_id": "13416560",
      "name": "companybao",
      "font_class": "companybao",
      "unicode": "e737",
      "unicode_decimal": 59191
    },
    {
      "icon_id": "13405446",
      "name": "tianjia",
      "font_class": "tianjia",
      "unicode": "e735",
      "unicode_decimal": 59189
    },
    {
      "icon_id": "13276508",
      "name": "twobg",
      "font_class": "twobg",
      "unicode": "e72e",
      "unicode_decimal": 59182
    },
    {
      "icon_id": "13276509",
      "name": "threebg",
      "font_class": "threebg",
      "unicode": "e72f",
      "unicode_decimal": 59183
    },
    {
      "icon_id": "13276510",
      "name": "dianfei",
      "font_class": "dianfei",
      "unicode": "e730",
      "unicode_decimal": 59184
    },
    {
      "icon_id": "13276511",
      "name": "onebg",
      "font_class": "onebg",
      "unicode": "e731",
      "unicode_decimal": 59185
    },
    {
      "icon_id": "13276512",
      "name": "fapiao",
      "font_class": "fapiao",
      "unicode": "e732",
      "unicode_decimal": 59186
    },
    {
      "icon_id": "13276513",
      "name": "email",
      "font_class": "email",
      "unicode": "e733",
      "unicode_decimal": 59187
    },
    {
      "icon_id": "13276514",
      "name": "ysqfp",
      "font_class": "ysqfp",
      "unicode": "e734",
      "unicode_decimal": 59188
    },
    {
      "icon_id": "13276502",
      "name": "cright",
      "font_class": "cright",
      "unicode": "e728",
      "unicode_decimal": 59176
    },
    {
      "icon_id": "13276503",
      "name": "cnext",
      "font_class": "cnext",
      "unicode": "e729",
      "unicode_decimal": 59177
    },
    {
      "icon_id": "13276504",
      "name": "one",
      "font_class": "one",
      "unicode": "e72a",
      "unicode_decimal": 59178
    },
    {
      "icon_id": "13276505",
      "name": "clast",
      "font_class": "clast",
      "unicode": "e72b",
      "unicode_decimal": 59179
    },
    {
      "icon_id": "13276506",
      "name": "three",
      "font_class": "three",
      "unicode": "e72c",
      "unicode_decimal": 59180
    },
    {
      "icon_id": "13276507",
      "name": "two",
      "font_class": "two",
      "unicode": "e72d",
      "unicode_decimal": 59181
    },
    {
      "icon_id": "13211426",
      "name": "windfan",
      "font_class": "windfan",
      "unicode": "e726",
      "unicode_decimal": 59174
    },
    {
      "icon_id": "13211427",
      "name": "pvfan",
      "font_class": "pvfan",
      "unicode": "e727",
      "unicode_decimal": 59175
    },
    {
      "icon_id": "13139529",
      "name": "zhankai",
      "font_class": "zhankai",
      "unicode": "e725",
      "unicode_decimal": 59173
    },
    {
      "icon_id": "13137175",
      "name": "alldone",
      "font_class": "alldone",
      "unicode": "e717",
      "unicode_decimal": 59159
    },
    {
      "icon_id": "13137177",
      "name": "btui",
      "font_class": "btui",
      "unicode": "e718",
      "unicode_decimal": 59160
    },
    {
      "icon_id": "13137178",
      "name": "movie",
      "font_class": "movie",
      "unicode": "e719",
      "unicode_decimal": 59161
    },
    {
      "icon_id": "13137179",
      "name": "dshen",
      "font_class": "dshen",
      "unicode": "e71a",
      "unicode_decimal": 59162
    },
    {
      "icon_id": "13137180",
      "name": "hulue",
      "font_class": "hulue1",
      "unicode": "e71b",
      "unicode_decimal": 59163
    },
    {
      "icon_id": "13137181",
      "name": "shouqi",
      "font_class": "shouqi",
      "unicode": "e71c",
      "unicode_decimal": 59164
    },
    {
      "icon_id": "13137182",
      "name": "undone",
      "font_class": "undone",
      "unicode": "e71d",
      "unicode_decimal": 59165
    },
    {
      "icon_id": "13137183",
      "name": "paifa",
      "font_class": "paifa1",
      "unicode": "e71e",
      "unicode_decimal": 59166
    },
    {
      "icon_id": "13137184",
      "name": "tuihui",
      "font_class": "tuihui",
      "unicode": "e71f",
      "unicode_decimal": 59167
    },
    {
      "icon_id": "13137185",
      "name": "quex",
      "font_class": "quex",
      "unicode": "e720",
      "unicode_decimal": 59168
    },
    {
      "icon_id": "13137186",
      "name": "tijiao",
      "font_class": "tijiao",
      "unicode": "e721",
      "unicode_decimal": 59169
    },
    {
      "icon_id": "13137189",
      "name": "xietiao",
      "font_class": "xietiao",
      "unicode": "e722",
      "unicode_decimal": 59170
    },
    {
      "icon_id": "13137190",
      "name": "yijie",
      "font_class": "yijie",
      "unicode": "e723",
      "unicode_decimal": 59171
    },
    {
      "icon_id": "13137191",
      "name": "weijie",
      "font_class": "weijie",
      "unicode": "e724",
      "unicode_decimal": 59172
    },
    {
      "icon_id": "13136591",
      "name": "checkup",
      "font_class": "checkup",
      "unicode": "e713",
      "unicode_decimal": 59155
    },
    {
      "icon_id": "13136592",
      "name": "checkend",
      "font_class": "checkend",
      "unicode": "e716",
      "unicode_decimal": 59158
    },
    {
      "icon_id": "12996380",
      "name": "dianb",
      "font_class": "dianb",
      "unicode": "e714",
      "unicode_decimal": 59156
    },
    {
      "icon_id": "12996381",
      "name": "changedb",
      "font_class": "changedb",
      "unicode": "e715",
      "unicode_decimal": 59157
    },
    {
      "icon_id": "12994943",
      "name": "moredata",
      "font_class": "moredata",
      "unicode": "e712",
      "unicode_decimal": 59154
    },
    {
      "icon_id": "12890041",
      "name": "rightarr",
      "font_class": "rightarr",
      "unicode": "e708",
      "unicode_decimal": 59144
    },
    {
      "icon_id": "12890042",
      "name": "leftarr",
      "font_class": "leftarr",
      "unicode": "e709",
      "unicode_decimal": 59145
    },
    {
      "icon_id": "12890043",
      "name": "xuanzhuan",
      "font_class": "xuanzhuan",
      "unicode": "e70a",
      "unicode_decimal": 59146
    },
    {
      "icon_id": "12890044",
      "name": "fanhui",
      "font_class": "fanhui",
      "unicode": "e70b",
      "unicode_decimal": 59147
    },
    {
      "icon_id": "12890045",
      "name": "chaoshi",
      "font_class": "chaoshi",
      "unicode": "e70c",
      "unicode_decimal": 59148
    },
    {
      "icon_id": "12890046",
      "name": "lingqu",
      "font_class": "lingqu",
      "unicode": "e70d",
      "unicode_decimal": 59149
    },
    {
      "icon_id": "12890047",
      "name": "biao",
      "font_class": "biao",
      "unicode": "e70e",
      "unicode_decimal": 59150
    },
    {
      "icon_id": "12890049",
      "name": "addman",
      "font_class": "addman",
      "unicode": "e70f",
      "unicode_decimal": 59151
    },
    {
      "icon_id": "12890050",
      "name": "gdxq",
      "font_class": "gdxq",
      "unicode": "e710",
      "unicode_decimal": 59152
    },
    {
      "icon_id": "12890051",
      "name": "jiedan",
      "font_class": "jiedan",
      "unicode": "e711",
      "unicode_decimal": 59153
    },
    {
      "icon_id": "12890024",
      "name": "liucheng01",
      "font_class": "liucheng",
      "unicode": "e702",
      "unicode_decimal": 59138
    },
    {
      "icon_id": "12890025",
      "name": "liucheng02",
      "font_class": "liucheng1",
      "unicode": "e703",
      "unicode_decimal": 59139
    },
    {
      "icon_id": "12890026",
      "name": "liucheng03",
      "font_class": "liucheng2",
      "unicode": "e704",
      "unicode_decimal": 59140
    },
    {
      "icon_id": "12890027",
      "name": "liucheng06",
      "font_class": "liucheng3",
      "unicode": "e705",
      "unicode_decimal": 59141
    },
    {
      "icon_id": "12890028",
      "name": "liucheng05",
      "font_class": "liucheng4",
      "unicode": "e706",
      "unicode_decimal": 59142
    },
    {
      "icon_id": "12890029",
      "name": "liuccheng04",
      "font_class": "liuccheng",
      "unicode": "e707",
      "unicode_decimal": 59143
    },
    {
      "icon_id": "12889273",
      "name": "zljc",
      "font_class": "zljc",
      "unicode": "e701",
      "unicode_decimal": 59137
    },
    {
      "icon_id": "12520605",
      "name": "zhenduan",
      "font_class": "zhenduan",
      "unicode": "e700",
      "unicode_decimal": 59136
    },
    {
      "icon_id": "12450165",
      "name": "yhulue",
      "font_class": "yhulue",
      "unicode": "e6fe",
      "unicode_decimal": 59134
    },
    {
      "icon_id": "12450166",
      "name": "ywancheng",
      "font_class": "ywancheng",
      "unicode": "e6ff",
      "unicode_decimal": 59135
    },
    {
      "icon_id": "12445251",
      "name": "paifa",
      "font_class": "paifa",
      "unicode": "e6fa",
      "unicode_decimal": 59130
    },
    {
      "icon_id": "12445252",
      "name": "zhank",
      "font_class": "zhank",
      "unicode": "e6fb",
      "unicode_decimal": 59131
    },
    {
      "icon_id": "12445253",
      "name": "chexiao",
      "font_class": "chexiao",
      "unicode": "e6fc",
      "unicode_decimal": 59132
    },
    {
      "icon_id": "12445255",
      "name": "shouq",
      "font_class": "shouq",
      "unicode": "e6fd",
      "unicode_decimal": 59133
    },
    {
      "icon_id": "12445250",
      "name": "hulue",
      "font_class": "hulue",
      "unicode": "e6f9",
      "unicode_decimal": 59129
    },
    {
      "icon_id": "12441233",
      "name": "newbuilt",
      "font_class": "newbuilt",
      "unicode": "e6f3",
      "unicode_decimal": 59123
    },
    {
      "icon_id": "12441234",
      "name": "closeall",
      "font_class": "closeall",
      "unicode": "e6f4",
      "unicode_decimal": 59124
    },
    {
      "icon_id": "12441235",
      "name": "powerstations",
      "font_class": "powerstations",
      "unicode": "e6f5",
      "unicode_decimal": 59125
    },
    {
      "icon_id": "12441236",
      "name": "export",
      "font_class": "export",
      "unicode": "e6f6",
      "unicode_decimal": 59126
    },
    {
      "icon_id": "12441237",
      "name": "save",
      "font_class": "save",
      "unicode": "e6f7",
      "unicode_decimal": 59127
    },
    {
      "icon_id": "12441238",
      "name": "goset",
      "font_class": "goset1",
      "unicode": "e6f8",
      "unicode_decimal": 59128
    },
    {
      "icon_id": "12362568",
      "name": "alert",
      "font_class": "alert",
      "unicode": "e6f2",
      "unicode_decimal": 59122
    },
    {
      "icon_id": "11982781",
      "name": "bumenx",
      "font_class": "bumenx",
      "unicode": "e6f1",
      "unicode_decimal": 59121
    },
    {
      "icon_id": "11267992",
      "name": "enlarge",
      "font_class": "enlarge",
      "unicode": "e6f0",
      "unicode_decimal": 59120
    },
    {
      "icon_id": "11167497",
      "name": "dzbb",
      "font_class": "dzbb",
      "unicode": "e6ee",
      "unicode_decimal": 59118
    },
    {
      "icon_id": "11167498",
      "name": "sebb",
      "font_class": "sebb",
      "unicode": "e6ef",
      "unicode_decimal": 59119
    },
    {
      "icon_id": "10906413",
      "name": "congra",
      "font_class": "congra",
      "unicode": "e6ed",
      "unicode_decimal": 59117
    },
    {
      "icon_id": "10906387",
      "name": "jxjh",
      "font_class": "jxjh",
      "unicode": "e6eb",
      "unicode_decimal": 59115
    },
    {
      "icon_id": "10906388",
      "name": "markdone",
      "font_class": "markdone",
      "unicode": "e6ec",
      "unicode_decimal": 59116
    },
    {
      "icon_id": "10906382",
      "name": "gzjs",
      "font_class": "gzjs",
      "unicode": "e6e8",
      "unicode_decimal": 59112
    },
    {
      "icon_id": "10906383",
      "name": "gzjh",
      "font_class": "gzjh",
      "unicode": "e6e9",
      "unicode_decimal": 59113
    },
    {
      "icon_id": "10906384",
      "name": "gzt",
      "font_class": "gzt",
      "unicode": "e6ea",
      "unicode_decimal": 59114
    },
    {
      "icon_id": "10731266",
      "name": "xiaon",
      "font_class": "xiaon",
      "unicode": "e6e5",
      "unicode_decimal": 59109
    },
    {
      "icon_id": "10731267",
      "name": "pro",
      "font_class": "pro1",
      "unicode": "e6e6",
      "unicode_decimal": 59110
    },
    {
      "icon_id": "10731268",
      "name": "anli",
      "font_class": "anli",
      "unicode": "e6e7",
      "unicode_decimal": 59111
    },
    {
      "icon_id": "10568316",
      "name": "arrow02",
      "font_class": "arrow",
      "unicode": "e6e2",
      "unicode_decimal": 59106
    },
    {
      "icon_id": "10568317",
      "name": "wrong",
      "font_class": "wrong",
      "unicode": "e6e3",
      "unicode_decimal": 59107
    },
    {
      "icon_id": "10568318",
      "name": "arrow01",
      "font_class": "arrow1",
      "unicode": "e6e4",
      "unicode_decimal": 59108
    },
    {
      "icon_id": "10568109",
      "name": "transfer",
      "font_class": "transfer",
      "unicode": "e6dd",
      "unicode_decimal": 59101
    },
    {
      "icon_id": "10568110",
      "name": "geli",
      "font_class": "geli",
      "unicode": "e6de",
      "unicode_decimal": 59102
    },
    {
      "icon_id": "10568111",
      "name": "cloudp",
      "font_class": "cloudp",
      "unicode": "e6df",
      "unicode_decimal": 59103
    },
    {
      "icon_id": "10568112",
      "name": "linkp",
      "font_class": "linkp",
      "unicode": "e6e0",
      "unicode_decimal": 59104
    },
    {
      "icon_id": "10568113",
      "name": "caiji",
      "font_class": "caiji",
      "unicode": "e6e1",
      "unicode_decimal": 59105
    },
    {
      "icon_id": "10568076",
      "name": "lamp",
      "font_class": "lamp",
      "unicode": "e6dc",
      "unicode_decimal": 59100
    },
    {
      "icon_id": "10550837",
      "name": "datajk",
      "font_class": "datajk",
      "unicode": "e6d9",
      "unicode_decimal": 59097
    },
    {
      "icon_id": "10550838",
      "name": "dataright",
      "font_class": "dataright",
      "unicode": "e6da",
      "unicode_decimal": 59098
    },
    {
      "icon_id": "10550840",
      "name": "hardware",
      "font_class": "hardware",
      "unicode": "e6db",
      "unicode_decimal": 59099
    },
    {
      "icon_id": "10549097",
      "name": "datagl",
      "font_class": "datagl",
      "unicode": "e6d8",
      "unicode_decimal": 59096
    },
    {
      "icon_id": "10221935",
      "name": "unmark",
      "font_class": "unmark",
      "unicode": "e6cc",
      "unicode_decimal": 59084
    },
    {
      "icon_id": "10221936",
      "name": "mark",
      "font_class": "mark1",
      "unicode": "e6d7",
      "unicode_decimal": 59095
    },
    {
      "icon_id": "10221868",
      "name": "enlarge2",
      "font_class": "enlarge2",
      "unicode": "e6cd",
      "unicode_decimal": 59085
    },
    {
      "icon_id": "10221869",
      "name": "upnext",
      "font_class": "upnext",
      "unicode": "e6ce",
      "unicode_decimal": 59086
    },
    {
      "icon_id": "10221870",
      "name": "windany",
      "font_class": "windany",
      "unicode": "e6d4",
      "unicode_decimal": 59092
    },
    {
      "icon_id": "10221871",
      "name": "sand",
      "font_class": "sand",
      "unicode": "e6d5",
      "unicode_decimal": 59093
    },
    {
      "icon_id": "10115125",
      "name": "skinpeel",
      "font_class": "skinpeel",
      "unicode": "e6cb",
      "unicode_decimal": 59083
    },
    {
      "icon_id": "9917179",
      "name": "uploading",
      "font_class": "uploading",
      "unicode": "e6cf",
      "unicode_decimal": 59087
    },
    {
      "icon_id": "9917180",
      "name": "condition",
      "font_class": "condition",
      "unicode": "e6d0",
      "unicode_decimal": 59088
    },
    {
      "icon_id": "9917181",
      "name": "uping",
      "font_class": "uping",
      "unicode": "e6d1",
      "unicode_decimal": 59089
    },
    {
      "icon_id": "9917182",
      "name": "status",
      "font_class": "status",
      "unicode": "e6d2",
      "unicode_decimal": 59090
    },
    {
      "icon_id": "9917183",
      "name": "ing",
      "font_class": "ing",
      "unicode": "e6d3",
      "unicode_decimal": 59091
    },
    {
      "icon_id": "9467406",
      "name": "wreport",
      "font_class": "wreport",
      "unicode": "e6c6",
      "unicode_decimal": 59078
    },
    {
      "icon_id": "9467407",
      "name": "warning",
      "font_class": "warning",
      "unicode": "e6c7",
      "unicode_decimal": 59079
    },
    {
      "icon_id": "9467408",
      "name": "datactrl",
      "font_class": "datactrl",
      "unicode": "e6c8",
      "unicode_decimal": 59080
    },
    {
      "icon_id": "9467409",
      "name": "gout",
      "font_class": "gout",
      "unicode": "e6c9",
      "unicode_decimal": 59081
    },
    {
      "icon_id": "9467410",
      "name": "windy",
      "font_class": "windy",
      "unicode": "e6ca",
      "unicode_decimal": 59082
    },
    {
      "icon_id": "9441219",
      "name": "gohome",
      "font_class": "gohome",
      "unicode": "e6c3",
      "unicode_decimal": 59075
    },
    {
      "icon_id": "9441220",
      "name": "screen",
      "font_class": "screen",
      "unicode": "e6c4",
      "unicode_decimal": 59076
    },
    {
      "icon_id": "9441221",
      "name": "control",
      "font_class": "control",
      "unicode": "e6c5",
      "unicode_decimal": 59077
    },
    {
      "icon_id": "9161256",
      "name": "go",
      "font_class": "go",
      "unicode": "e6bd",
      "unicode_decimal": 59069
    },
    {
      "icon_id": "9161257",
      "name": "go2",
      "font_class": "go2",
      "unicode": "e6be",
      "unicode_decimal": 59070
    },
    {
      "icon_id": "9161238",
      "name": "back",
      "font_class": "back2",
      "unicode": "e6bf",
      "unicode_decimal": 59071
    },
    {
      "icon_id": "9161239",
      "name": "goodz",
      "font_class": "goodz",
      "unicode": "e6c0",
      "unicode_decimal": 59072
    },
    {
      "icon_id": "9161240",
      "name": "refresh2",
      "font_class": "refresh2",
      "unicode": "e6c1",
      "unicode_decimal": 59073
    },
    {
      "icon_id": "9161241",
      "name": "pro",
      "font_class": "pro",
      "unicode": "e6c2",
      "unicode_decimal": 59074
    },
    {
      "icon_id": "8580942",
      "name": "await",
      "font_class": "await",
      "unicode": "e6ba",
      "unicode_decimal": 59066
    },
    {
      "icon_id": "8580943",
      "name": "repair",
      "font_class": "repair",
      "unicode": "e6bb",
      "unicode_decimal": 59067
    },
    {
      "icon_id": "8580944",
      "name": "suspend",
      "font_class": "suspend",
      "unicode": "e6bc",
      "unicode_decimal": 59068
    },
    {
      "icon_id": "8126344",
      "name": "fengta",
      "font_class": "fengta",
      "unicode": "e6b9",
      "unicode_decimal": 59065
    },
    {
      "icon_id": "7807462",
      "name": "mark",
      "font_class": "mark",
      "unicode": "e6b6",
      "unicode_decimal": 59062
    },
    {
      "icon_id": "7807463",
      "name": "da",
      "font_class": "da",
      "unicode": "e6b7",
      "unicode_decimal": 59063
    },
    {
      "icon_id": "7807464",
      "name": "trends",
      "font_class": "trends",
      "unicode": "e6b8",
      "unicode_decimal": 59064
    },
    {
      "icon_id": "7354640",
      "name": "mapman",
      "font_class": "mapman",
      "unicode": "e6b5",
      "unicode_decimal": 59061
    },
    {
      "icon_id": "7016929",
      "name": "syz",
      "font_class": "syz",
      "unicode": "e6b4",
      "unicode_decimal": 59060
    },
    {
      "icon_id": "6998330",
      "name": "plan",
      "font_class": "plan",
      "unicode": "e6b3",
      "unicode_decimal": 59059
    },
    {
      "icon_id": "6998289",
      "name": "addto",
      "font_class": "addto",
      "unicode": "e6b1",
      "unicode_decimal": 59057
    },
    {
      "icon_id": "6998290",
      "name": "viewplan",
      "font_class": "viewplan",
      "unicode": "e6b2",
      "unicode_decimal": 59058
    },
    {
      "icon_id": "6996572",
      "name": "neglect",
      "font_class": "neglect",
      "unicode": "e6ac",
      "unicode_decimal": 59052
    },
    {
      "icon_id": "6996573",
      "name": "cleaning-model ",
      "font_class": "cleaning-model",
      "unicode": "e6ad",
      "unicode_decimal": 59053
    },
    {
      "icon_id": "6996574",
      "name": "todo",
      "font_class": "todo",
      "unicode": "e6ae",
      "unicode_decimal": 59054
    },
    {
      "icon_id": "6996575",
      "name": "inefficient",
      "font_class": "inefficient",
      "unicode": "e6af",
      "unicode_decimal": 59055
    },
    {
      "icon_id": "6996600",
      "name": "cancellation",
      "font_class": "cancellation",
      "unicode": "e6b0",
      "unicode_decimal": 59056
    },
    {
      "icon_id": "6621034",
      "name": "acb",
      "font_class": "acb",
      "unicode": "e6aa",
      "unicode_decimal": 59050
    },
    {
      "icon_id": "6621035",
      "name": "windgo",
      "font_class": "windgo",
      "unicode": "e6ab",
      "unicode_decimal": 59051
    },
    {
      "icon_id": "6375197",
      "name": "download",
      "font_class": "download",
      "unicode": "e6a9",
      "unicode_decimal": 59049
    },
    {
      "icon_id": "6375079",
      "name": "planed",
      "font_class": "planed",
      "unicode": "e6a7",
      "unicode_decimal": 59047
    },
    {
      "icon_id": "6375080",
      "name": "log",
      "font_class": "log",
      "unicode": "e6a8",
      "unicode_decimal": 59048
    },
    {
      "icon_id": "6200798",
      "name": "count",
      "font_class": "count",
      "unicode": "e6a3",
      "unicode_decimal": 59043
    },
    {
      "icon_id": "6200799",
      "name": "running",
      "font_class": "running",
      "unicode": "e6a4",
      "unicode_decimal": 59044
    },
    {
      "icon_id": "6200800",
      "name": "device-data",
      "font_class": "device-data",
      "unicode": "e6a5",
      "unicode_decimal": 59045
    },
    {
      "icon_id": "6200809",
      "name": "station-data",
      "font_class": "station-data",
      "unicode": "e6a6",
      "unicode_decimal": 59046
    },
    {
      "icon_id": "6092913",
      "name": "jidian",
      "font_class": "jidian",
      "unicode": "e6a2",
      "unicode_decimal": 59042
    },
    {
      "icon_id": "6035106",
      "name": "arrowgo",
      "font_class": "arrowgo",
      "unicode": "e6a1",
      "unicode_decimal": 59041
    },
    {
      "icon_id": "6006229",
      "name": "triangle",
      "font_class": "triangle",
      "unicode": "e6a0",
      "unicode_decimal": 59040
    },
    {
      "icon_id": "6005957",
      "name": "station-manage",
      "font_class": "station-manage",
      "unicode": "e69e",
      "unicode_decimal": 59038
    },
    {
      "icon_id": "6005958",
      "name": "set",
      "font_class": "goset",
      "unicode": "e69f",
      "unicode_decimal": 59039
    },
    {
      "icon_id": "6005684",
      "name": "goon",
      "font_class": "goon",
      "unicode": "e698",
      "unicode_decimal": 59032
    },
    {
      "icon_id": "5523743",
      "name": "usermanage",
      "font_class": "usermanage",
      "unicode": "e68f",
      "unicode_decimal": 59023
    },
    {
      "icon_id": "5523744",
      "name": "department",
      "font_class": "department",
      "unicode": "e690",
      "unicode_decimal": 59024
    },
    {
      "icon_id": "5523745",
      "name": "member",
      "font_class": "member",
      "unicode": "e691",
      "unicode_decimal": 59025
    },
    {
      "icon_id": "5523748",
      "name": "role",
      "font_class": "role",
      "unicode": "e692",
      "unicode_decimal": 59026
    },
    {
      "icon_id": "5523764",
      "name": "powerstation",
      "font_class": "powerstation",
      "unicode": "e693",
      "unicode_decimal": 59027
    },
    {
      "icon_id": "5523765",
      "name": "search",
      "font_class": "search",
      "unicode": "e694",
      "unicode_decimal": 59028
    },
    {
      "icon_id": "5523766",
      "name": "set01",
      "font_class": "set",
      "unicode": "e695",
      "unicode_decimal": 59029
    },
    {
      "icon_id": "5523767",
      "name": "set02",
      "font_class": "set1",
      "unicode": "e696",
      "unicode_decimal": 59030
    },
    {
      "icon_id": "5523768",
      "name": "edit",
      "font_class": "edit",
      "unicode": "e697",
      "unicode_decimal": 59031
    },
    {
      "icon_id": "5523770",
      "name": "elecmanage",
      "font_class": "elecmanage",
      "unicode": "e699",
      "unicode_decimal": 59033
    },
    {
      "icon_id": "5523771",
      "name": "remove",
      "font_class": "remove",
      "unicode": "e69a",
      "unicode_decimal": 59034
    },
    {
      "icon_id": "5523773",
      "name": "enable",
      "font_class": "enable",
      "unicode": "e69b",
      "unicode_decimal": 59035
    },
    {
      "icon_id": "5523774",
      "name": "disable",
      "font_class": "disable",
      "unicode": "e69c",
      "unicode_decimal": 59036
    },
    {
      "icon_id": "5523779",
      "name": "examine",
      "font_class": "examine1",
      "unicode": "e69d",
      "unicode_decimal": 59037
    },
    {
      "icon_id": "5515391",
      "name": "xb",
      "font_class": "xb",
      "unicode": "e68b",
      "unicode_decimal": 59019
    },
    {
      "icon_id": "5515393",
      "name": "hl",
      "font_class": "hl",
      "unicode": "e68c",
      "unicode_decimal": 59020
    },
    {
      "icon_id": "5515412",
      "name": "elecnetting",
      "font_class": "elecnetting",
      "unicode": "e68d",
      "unicode_decimal": 59021
    },
    {
      "icon_id": "5515414",
      "name": "weather",
      "font_class": "weather",
      "unicode": "e68e",
      "unicode_decimal": 59022
    },
    {
      "icon_id": "5515171",
      "name": "pvs",
      "font_class": "pvs",
      "unicode": "e688",
      "unicode_decimal": 59016
    },
    {
      "icon_id": "5515172",
      "name": "nb1",
      "font_class": "nb",
      "unicode": "e689",
      "unicode_decimal": 59017
    },
    {
      "icon_id": "5515173",
      "name": "nb2",
      "font_class": "nb1",
      "unicode": "e68a",
      "unicode_decimal": 59018
    },
    {
      "icon_id": "5515136",
      "name": "revoke",
      "font_class": "revoke",
      "unicode": "e67e",
      "unicode_decimal": 59006
    },
    {
      "icon_id": "5515137",
      "name": "lifted",
      "font_class": "lifted",
      "unicode": "e67f",
      "unicode_decimal": 59007
    },
    {
      "icon_id": "5515138",
      "name": "tranlist",
      "font_class": "tranlist",
      "unicode": "e680",
      "unicode_decimal": 59008
    },
    {
      "icon_id": "5515139",
      "name": "manual",
      "font_class": "manual",
      "unicode": "e681",
      "unicode_decimal": 59009
    },
    {
      "icon_id": "5515143",
      "name": "refresh",
      "font_class": "refresh",
      "unicode": "e683",
      "unicode_decimal": 59011
    },
    {
      "icon_id": "5515144",
      "name": "alarm2",
      "font_class": "alarm1",
      "unicode": "e685",
      "unicode_decimal": 59013
    },
    {
      "icon_id": "5515096",
      "name": "alarm",
      "font_class": "alarm",
      "unicode": "e682",
      "unicode_decimal": 59010
    },
    {
      "icon_id": "5514975",
      "name": "monitoring",
      "font_class": "monitoring",
      "unicode": "e687",
      "unicode_decimal": 59015
    },
    {
      "icon_id": "5514407",
      "name": "grid",
      "font_class": "grid",
      "unicode": "e67a",
      "unicode_decimal": 59002
    },
    {
      "icon_id": "5514408",
      "name": "map",
      "font_class": "map",
      "unicode": "e67b",
      "unicode_decimal": 59003
    },
    {
      "icon_id": "5514423",
      "name": "upstream",
      "font_class": "upstream",
      "unicode": "e67c",
      "unicode_decimal": 59004
    },
    {
      "icon_id": "5514424",
      "name": "downstream",
      "font_class": "downstream",
      "unicode": "e67d",
      "unicode_decimal": 59005
    },
    {
      "icon_id": "5514445",
      "name": "more",
      "font_class": "more",
      "unicode": "e684",
      "unicode_decimal": 59012
    },
    {
      "icon_id": "5514448",
      "name": "outage",
      "font_class": "outage",
      "unicode": "e686",
      "unicode_decimal": 59014
    },
    {
      "icon_id": "5405146",
      "name": "lookall",
      "font_class": "lookall",
      "unicode": "e677",
      "unicode_decimal": 58999
    },
    {
      "icon_id": "5405147",
      "name": "drawing",
      "font_class": "drawing",
      "unicode": "e678",
      "unicode_decimal": 59000
    },
    {
      "icon_id": "5405148",
      "name": "table",
      "font_class": "table",
      "unicode": "e679",
      "unicode_decimal": 59001
    },
    {
      "icon_id": "5404213",
      "name": "help",
      "font_class": "help",
      "unicode": "e664",
      "unicode_decimal": 58980
    },
    {
      "icon_id": "5404214",
      "name": "doing",
      "font_class": "doing",
      "unicode": "e66e",
      "unicode_decimal": 58990
    },
    {
      "icon_id": "5403821",
      "name": "quit",
      "font_class": "quit",
      "unicode": "e66f",
      "unicode_decimal": 58991
    },
    {
      "icon_id": "5403822",
      "name": "menu_open",
      "font_class": "menu-open",
      "unicode": "e670",
      "unicode_decimal": 58992
    },
    {
      "icon_id": "5403823",
      "name": "menu_fold",
      "font_class": "menu-fold",
      "unicode": "e671",
      "unicode_decimal": 58993
    },
    {
      "icon_id": "5403824",
      "name": "home",
      "font_class": "home",
      "unicode": "e672",
      "unicode_decimal": 58994
    },
    {
      "icon_id": "5403825",
      "name": "password",
      "font_class": "password1",
      "unicode": "e673",
      "unicode_decimal": 58995
    },
    {
      "icon_id": "5403826",
      "name": "pulldown",
      "font_class": "pulldown",
      "unicode": "e674",
      "unicode_decimal": 58996
    },
    {
      "icon_id": "5403827",
      "name": "reorder",
      "font_class": "reorder",
      "unicode": "e675",
      "unicode_decimal": 58997
    },
    {
      "icon_id": "5403894",
      "name": "message",
      "font_class": "message",
      "unicode": "e676",
      "unicode_decimal": 58998
    },
    {
      "icon_id": "5403784",
      "name": "content",
      "font_class": "content",
      "unicode": "e654",
      "unicode_decimal": 58964
    },
    {
      "icon_id": "5403785",
      "name": "close",
      "font_class": "close1",
      "unicode": "e655",
      "unicode_decimal": 58965
    },
    {
      "icon_id": "5403786",
      "name": "filter",
      "font_class": "filter",
      "unicode": "e656",
      "unicode_decimal": 58966
    },
    {
      "icon_id": "5403787",
      "name": "arrowr",
      "font_class": "arrowr",
      "unicode": "e657",
      "unicode_decimal": 58967
    },
    {
      "icon_id": "5403788",
      "name": "begin",
      "font_class": "begin",
      "unicode": "e658",
      "unicode_decimal": 58968
    },
    {
      "icon_id": "5403789",
      "name": "del",
      "font_class": "del",
      "unicode": "e659",
      "unicode_decimal": 58969
    },
    {
      "icon_id": "5403790",
      "name": "date",
      "font_class": "date",
      "unicode": "e65a",
      "unicode_decimal": 58970
    },
    {
      "icon_id": "5403791",
      "name": "doned",
      "font_class": "doned",
      "unicode": "e65b",
      "unicode_decimal": 58971
    },
    {
      "icon_id": "5403792",
      "name": "gd02",
      "font_class": "gd2",
      "unicode": "e65c",
      "unicode_decimal": 58972
    },
    {
      "icon_id": "5403793",
      "name": "done",
      "font_class": "done",
      "unicode": "e65d",
      "unicode_decimal": 58973
    },
    {
      "icon_id": "5403794",
      "name": "gd01",
      "font_class": "gd1",
      "unicode": "e65e",
      "unicode_decimal": 58974
    },
    {
      "icon_id": "5403795",
      "name": "gd03",
      "font_class": "gd3",
      "unicode": "e65f",
      "unicode_decimal": 58975
    },
    {
      "icon_id": "5403796",
      "name": "examine",
      "font_class": "examine",
      "unicode": "e660",
      "unicode_decimal": 58976
    },
    {
      "icon_id": "5403797",
      "name": "gd04",
      "font_class": "gd4",
      "unicode": "e661",
      "unicode_decimal": 58977
    },
    {
      "icon_id": "5403798",
      "name": "look",
      "font_class": "look",
      "unicode": "e662",
      "unicode_decimal": 58978
    },
    {
      "icon_id": "5403799",
      "name": "ha",
      "font_class": "ha",
      "unicode": "e663",
      "unicode_decimal": 58979
    },
    {
      "icon_id": "5403801",
      "name": "reject",
      "font_class": "reject",
      "unicode": "e665",
      "unicode_decimal": 58981
    },
    {
      "icon_id": "5403802",
      "name": "stop",
      "font_class": "stop",
      "unicode": "e666",
      "unicode_decimal": 58982
    },
    {
      "icon_id": "5403803",
      "name": "review",
      "font_class": "review",
      "unicode": "e667",
      "unicode_decimal": 58983
    },
    {
      "icon_id": "5403804",
      "name": "pvlogo",
      "font_class": "pvlogo",
      "unicode": "e668",
      "unicode_decimal": 58984
    },
    {
      "icon_id": "5403805",
      "name": "windlogo",
      "font_class": "windlogo",
      "unicode": "e669",
      "unicode_decimal": 58985
    },
    {
      "icon_id": "5403806",
      "name": "release",
      "font_class": "release",
      "unicode": "e66a",
      "unicode_decimal": 58986
    },
    {
      "icon_id": "5403807",
      "name": "arrowleft",
      "font_class": "arrowleft",
      "unicode": "e66b",
      "unicode_decimal": 58987
    },
    {
      "icon_id": "5403808",
      "name": "last",
      "font_class": "last",
      "unicode": "e66c",
      "unicode_decimal": 58988
    },
    {
      "icon_id": "5403809",
      "name": "next",
      "font_class": "next",
      "unicode": "e66d",
      "unicode_decimal": 58989
    },
    {
      "icon_id": "5353394",
      "name": "user",
      "font_class": "user",
      "unicode": "e631",
      "unicode_decimal": 58929
    },
    {
      "icon_id": "5353391",
      "name": "join",
      "font_class": "join",
      "unicode": "e630",
      "unicode_decimal": 58928
    },
    {
      "icon_id": "5353383",
      "name": "phone",
      "font_class": "phone",
      "unicode": "e62f",
      "unicode_decimal": 58927
    },
    {
      "icon_id": "5353375",
      "name": "password",
      "font_class": "password",
      "unicode": "e62e",
      "unicode_decimal": 58926
    },
    {
      "icon_id": "5352996",
      "name": "question1",
      "font_class": "question",
      "unicode": "e62b",
      "unicode_decimal": 58923
    },
    {
      "icon_id": "5352992",
      "name": "back",
      "font_class": "back",
      "unicode": "e62a",
      "unicode_decimal": 58922
    },
    {
      "icon_id": "5352987",
      "name": "done",
      "font_class": "close",
      "unicode": "e629",
      "unicode_decimal": 58921
    },
    {
      "icon_id": "5352985",
      "name": "alert_01",
      "font_class": "alert_01",
      "unicode": "e628",
      "unicode_decimal": 58920
    }
  ]
}
